setup.py
pqcom/__init__.py
pqcom/pqcom.py
pqcom/pqcom_about_ui.py
pqcom/pqcom_serial.py
pqcom/pqcom_setup_ui.py
pqcom/pqcom_translator.py
pqcom/pqcom_ui.py
pqcom/util.py
pqcom.egg-info/PKG-INFO
pqcom.egg-info/SOURCES.txt
pqcom.egg-info/dependency_links.txt
pqcom.egg-info/entry_points.txt
pqcom.egg-info/requires.txt
pqcom.egg-info/top_level.txt
pqcom/img/0x.svg
pqcom/img/about.svg
pqcom/img/clear.svg
pqcom/img/ex.svg
pqcom/img/hex.svg
pqcom/img/new.svg
pqcom/img/normal.svg
pqcom/img/pqcom-logo-expanded.png
pqcom/img/pqcom-logo.png
pqcom/img/run.svg
pqcom/img/settings.svg
pqcom/img/star.svg