Metadata-Version: 1.1
Name: pqcom
Version: 0.5.1
Summary: A cross platform serial tool
Home-page: https://github.com/xiongyihui/pqcom
Author: Yihui Xiong
Author-email: xiongyihui3@gmail.com
License: MIT
Keywords: sample setuptools development
Platform: UNKNOWN
Classifier: Development Status :: 3 - Alpha
Classifier: Intended Audience :: Developers
Classifier: Topic :: Software Development :: Build Tools
Classifier: License :: OSI Approved :: MIT License
